memoryinvestguide/__init__.py
memoryinvestguide/main.py
memoryinvestguide/prompts.py
memoryinvestguide-2025.12.21135045.dist-info/METADATA
memoryinvestguide-2025.12.21135045.dist-info/WHEEL
memoryinvestguide-2025.12.21135045.dist-info/top_level.txt
memoryinvestguide-2025.12.21135045.dist-info/RECORD
