Metadata-Version: 2.4
Name: memoryinvestguide
Version: 2025.12.21135045
Summary: A new package designed to help users navigate the volatile memory market by providing structured, long-term investment strategies. Users input their current financial situation, risk tolerance, and in
Author-email: memoryinvestguide <hi@eugene.plus>
License: MIT
Project-URL: Homepage, https://github.com/chigwell/memoryinvestguide
Requires-Python: >=3.9
Requires-Dist: langchain-llm7>=0.0.0
Requires-Dist: llmatch-messages>=0.0.0
Requires-Dist: langchain-core>=0.3.0
